Metadata-Version: 2.1
Name: snap-numpy-stubs
Version: 4.10.21
Summary: UNKNOWN
Home-page: https://github.com/kmadman33/snap-numpy-stubs
Author: kmadman33
Author-email: kmadman33@gmail.com
License: MIT
Project-URL: Documentation, https://snap-numpy-stubs.readthedocs.io
Project-URL: Source, https://github.com/kmadman33/snap-numpy-stubs
Platform: UNKNOWN
Classifier: Development Status :: 5 - Production/Stable
Classifier: Intended Audience :: Developers
Classifier: Natural Language :: English
Classifier: License :: OSI Approved :: MIT License
